pensum/__init__.py
pensum/__main__.py
pensum/base.py
pensum/builders.py
pensum/common.py
pensum/config.py
pensum/note.py
pensum/notes.py
pensum/pm.py
pensum/psm.py
pensum/topics/__init__.py
pensum/topics/buildformats.md
pensum/topics/folders.md
pensum/topics/license.md
pensum/topics/pm.md
pensum/topics/psm.md
pensum-2022.3.23.dist-info/LICENSE
pensum-2022.3.23.dist-info/METADATA
pensum-2022.3.23.dist-info/WHEEL
pensum-2022.3.23.dist-info/entry_points.txt
pensum-2022.3.23.dist-info/top_level.txt
pensum-2022.3.23.dist-info/RECORD
