Metadata-Version: 2.1
Name: pensum
Version: 2022.3.23
Summary: Command lines reminder
Home-page: UNKNOWN
Author: Étienne Nadji
Author-email: etnadji@eml.cc
License: GNU General Public License v3 or later (GPLv3+)
Project-URL: Source Code, https://framagit.org/etnadji/pensum
Project-URL: Issue tracker, https://framagit.org/etnadji/pensum/-/issues
Project-URL: Documentation, https://framagit.org/etnadji/pensum/-/wikis/Pensum
Project-URL: License, https://framagit.org/etnadji/pensum/-/blob/main/LICENSE
Platform: any
Classifier: Topic :: Documentation
Classifier: Operating System :: OS Independent
Classifier: Intended Audience :: Developers
Classifier: Intended Audience :: End Users/Desktop
Classifier: Programming Language :: Python :: 3
Classifier: Programming Language :: Python :: 3.8
Classifier: License :: OSI Approved :: GNU Affero General Public License v3 or later (AGPLv3+)
Requires-Python: >=3.8
Requires-Dist: appdirs
Requires-Dist: docopt
Requires-Dist: pypandoc
Requires-Dist: rich
Requires-Dist: stop-words
